README.md
setup.py
qth_yarp/__init__.py
qth_yarp/version.py
qth_yarp.egg-info/PKG-INFO
qth_yarp.egg-info/SOURCES.txt
qth_yarp.egg-info/dependency_links.txt
qth_yarp.egg-info/requires.txt
qth_yarp.egg-info/top_level.txt