Metadata-Version: 1.1
Name: qth-yarp
Version: 0.2.0
Summary: Library for writing reactive programming style scripts with Qth.
Home-page: https://github.com/mossblaser/qth_yarp
Author: Jonathan Heathcote
Author-email: UNKNOWN
License: GPLv2
Keywords: mqtt asyncio home-automation messaging home automation yarp reactive
Platform: UNKNOWN
Classifier: Development Status :: 3 - Alpha
Classifier: Intended Audience :: Developers
Classifier: License :: OSI Approved :: GNU General Public License v2 (GPLv2)
Classifier: Operating System :: POSIX :: Linux
Classifier: Operating System :: Microsoft :: Windows
Classifier: Operating System :: MacOS
Classifier: Programming Language :: Python :: 3
Classifier: Programming Language :: Python :: 3.4
Classifier: Programming Language :: Python :: 3.5
